exorde/__init__.py
exorde/bindings.py
exorde/formated.py
exorde/ipfs/__init__.py
exorde/ipfs/bindings.py
exorde/ipfs/schema.json
exorde/ipfs/setup.py
exorde/playwright/__init__.py
exorde/playwright/bindings.py
exorde/playwright/setup.py
exorde/protocol/__init__.py
exorde/protocol/bindings.py
exorde/protocol/configuration.yaml
exorde/protocol/setup.py
exorde/reddit/__init__.py
exorde/reddit/bindings.py
exorde/reddit/setup.py
exorde/spotting/__init__.py
exorde/spotting/bindings.py
exorde/translation/__init__.py
exorde/translation/bindings.py
exorde/translation/setup.py
exorde/twitter/__init__.py
exorde/twitter/bindings.py
exorde/twitter/setup.py
exorde/validation/__init__.py
exorde/validation/bindings.py
exorde/validation/validators.py
exorde/xyake/__init__.py
exorde/xyake/bindings.py
exorde/xyake/setup.py
exorde-0.1.1.dist-info/METADATA
exorde-0.1.1.dist-info/WHEEL
exorde-0.1.1.dist-info/entry_points.txt
exorde-0.1.1.dist-info/top_level.txt
exorde-0.1.1.dist-info/RECORD
