Metadata-Version: 2.1
Name: exorde
Version: 0.1.1
Summary: Exorde CLI
License: MIT
Requires-Dist: web3
Requires-Dist: yake
Requires-Dist: aiohttp
Requires-Dist: lxml
Requires-Dist: playwright (==1.31.1)
Requires-Dist: aiosow
Requires-Dist: pyyaml
Requires-Dist: argostranslate
Requires-Dist: python-dateutil
Requires-Dist: fasttext-langdetect
Requires-Dist: playwright-stealth
